queue_sqlite_core-0.2.1.dist-info/METADATA
queue_sqlite_core-0.2.1.dist-info/WHEEL
queue_sqlite_core/__init__.py
queue_sqlite_core/__init__.pyi
queue_sqlite_core/py.typed
queue_sqlite_core/queue_sqlite_core.cp313-win_amd64.pyd
queue_sqlite_core-0.2.1.dist-info/RECORD
