Metadata-Version: 2.4
Name: queue_sqlite_core
Version: 0.2.1
Classifier: Programming Language :: Rust
Classifier: Programming Language :: Python :: Implementation :: CPython
Classifier: Programming Language :: Python :: Implementation :: PyPy
Summary: Python bindings for queue_sqlite_core Rust library
Requires-Python: >=3.7
